{"texts":[{"content":"07326","x":719,"y":1574,"w":41,"h":16},{"content":"서울시영등포구국제금융로","x":760,"y":1573,"w":170,"h":17},{"content":"10","x":932,"y":1574,"w":17,"h":16},{"content":"국제금융센터","x":949,"y":1573,"w":81,"h":17},{"content":"Two IFC 27","x":1033,"y":1574,"w":70,"h":16},{"content":"층","x":1102,"y":1573,"w":15,"h":16},{"content":"AIG","x":876,"y":1606,"w":46,"h":28},{"content":"손해보험주식회사","x":923,"y":1604,"w":194,"h":26},{"content":"상품설명서","x":240,"y":61,"w":200,"h":44},{"content":"무배당 AIG 든든한 간편암보험2604(325간편심사형)(10년갱신형)","x":82,"y":146,"w":1039,"h":36},{"content":"설계번호 : 942696462419","x":886,"y":197,"w":252,"h":22},{"content":"상품개발자","x":69,"y":1579,"w":80,"h":16},{"content":"윤인선((02)2260-6800)","x":166,"y":1579,"w":181,"h":16},{"content":"모집인소속","x":69,"y":1597,"w":80,"h":16},{"content":"보험대리점 ㈜에이아이지어드바이저_LTC2(AA)","x":166,"y":1597,"w":343,"h":16},{"content":"모","x":69,"y":1616,"w":15,"h":16},{"content":"집","x":101,"y":1616,"w":15,"h":16},{"content":"인","x":133,"y":1616,"w":15,"h":16},{"content":"위지영 (고유번호 : 20150485120007)","x":166,"y":1616,"w":279,"h":16},{"content":"연","x":69,"y":1635,"w":15,"h":16},{"content":"락","x":101,"y":1635,"w":15,"h":16},{"content":"처","x":133,"y":1635,"w":15,"h":16},{"content":"(02)6430-4700","x":166,"y":1635,"w":124,"h":16},{"content":"발행일시","x":69,"y":1654,"w":80,"h":16},{"content":"2026년 04월 10일","x":166,"y":1654,"w":145,"h":16},{"content":"고객센터","x":69,"y":1673,"w":80,"h":16},{"content":"1544-2792","x":166,"y":1673,"w":91,"h":16},{"content":"관리번호","x":756,"y":1633,"w":80,"h":16},{"content":":  AIG 상품관리 제2026-4-TM-P035호","x":854,"y":1633,"w":284,"h":16},{"content":"사례1: 갱년기 호르몬제 복용중이나 중년에 대부분 복용하는 것으로 질병으로 생각하지 않아 청약 시 고지하지 않았으나","x":131,"y":280,"w":946,"h":19},{"content":"해당 사유로 계약이 해지됨","x":131,"y":305,"w":269,"h":19},{"content":"사례2: 경미한 접촉사고로 몇 일 통원치료 후 별다른 증상이 없어 보험 가입 시 해당 사고를 고지하지 않았으나 해당 사유로","x":131,"y":330,"w":980,"h":19},{"content":"계약이 해지됨","x":131,"y":355,"w":168,"h":19},{"content":"사례3: C씨는 모집인에게 간질환으로 치료를 받은 사실을 구두로 얘기하고 보험을 가입한 후 간경화로 입원치료를 받고","x":131,"y":379,"w":943,"h":19},{"content":"청구하였으나 가입 시 간질환 치료사실을 고지하지 않았다는 사유로 계약을 해지하고 보험금도 지급하지 않음","x":131,"y":404,"w":923,"h":19},{"content":"※ 유의사항:","x":131,"y":429,"w":107,"h":19},{"content":"보험 청약 시 청약서 계약 전 알릴의무에 해당하는 병력 및 치료사실에 대해서는 사실대로 알려야 하며, 사실대로","x":238,"y":429,"w":896,"h":19},{"content":"알리지 않은 경우 계약 전 알릴의무 위반으로 계약이 해지되거나 보험금이 지급되지 않을 수 있습니다. 고지수령권이 없는","x":131,"y":454,"w":964,"h":19},{"content":"모집인에게 구두 통보한 것은 고지한 것이 아니며, 청약서에 최종 기재되어야만 고지의무를 이행한 것으로 봅니다.","x":131,"y":479,"w":902,"h":19},{"content":"보험 가입 시 청약서의 기재여부를 반드시 확인하고 서명하시기 바랍니다. 전화 등 통신수단을 통해 가입한 경우 판매자의","x":131,"y":504,"w":964,"h":19},{"content":"질문에 답하고 이를 녹음하는 방식으로 계약 전 알릴의무를 이행하여야 하므로 답변에 신중하여야 합니다.","x":131,"y":529,"w":838,"h":19},{"content":"② 부담보(특정부위·질병 부담보) 관련 사례","x":106,"y":559,"w":352,"h":19},{"content":"C씨는 2019. 4. 1 보험 가입 시 2018. 12월 건강검진 시 왼쪽 유방에 양성 석회화 소견을 받은 사실을 고지하고 보험 가입 후","x":131,"y":590,"w":983,"h":19},{"content":"2019. 6월 유방암으로 진단받고보험금을 청구하였으나 유방부위에 보장개시일로부터 5년간 부담보 조건으로 보험이 가입되어","x":131,"y":615,"w":987,"h":19},{"content":"보험금이 지급되지 않음","x":131,"y":640,"w":188,"h":19},{"content":"※ 유의(참고)사항 :","x":131,"y":664,"w":160,"h":19},{"content":"보험계약을 체결할 당시 피보험자의 건강상태가 보험회사가 정한 기준에 적합하지 않을 경우 특정부위에 발","x":291,"y":664,"w":850,"h":19},{"content":"생한 질병이나 특정 질병에대하여 면책하는 조건으로 계약을 체결할 수 있으며, 계약일(부활일)로부터 회사가 정한 면책기간(부","x":131,"y":689,"w":999,"h":19},{"content":"담보 기간)중에 부담보 부위·질환 분류표에서정한 부위에 생긴 질병 또는 특정 질병을 직접적인 원인으로 보험계약에서 정한","x":131,"y":714,"w":991,"h":19},{"content":"보험금 지급사유가 발생한 경우에는 보험금을 지급하지 않으며, 보험료 납입면제 사유가 발생한 경우에 회사는 납입을 면제하지","x":131,"y":739,"w":1008,"h":19},{"content":"않습니다.보험계약 체결 시 부담보(특정부위·질병 부담보) 조건으로 보험이 가입되는 지 청약서와증권을 면밀하게 살펴야 합니","x":131,"y":764,"w":1002,"h":19},{"content":"다.","x":131,"y":789,"w":23,"h":19},{"content":"③ (질병/상해)수술비 관련 사례","x":106,"y":819,"w":249,"h":19},{"content":"사례1: A씨는 보험 가입 후 신경성형술을 시행 후 질병수술비를 청구하였으나, 해당 보험 상품의 약관상 수술의 정의에","x":131,"y":850,"w":936,"h":19},{"content":"해당하지 않아 보험금 지급이 거절됨","x":131,"y":875,"w":346,"h":19},{"content":"사례2: B씨는 손가락이 찢어져 봉합술을 시행하고 상해수술비를 청구하였으나, 해당 보험 상품의 약관상 수술의 정의에","x":131,"y":900,"w":939,"h":19},{"content":"해당하지 않아 보험금 지급이 거절됨","x":131,"y":924,"w":346,"h":19},{"content":"※ 유의사항:","x":131,"y":949,"w":107,"h":19},{"content":"질병/상해 수술비 특별약관에서는 ‘수술’의 정의를 명시하고 있으며, 해당 치료 행위가 약관에 정한 ‘수술’의","x":238,"y":949,"w":896,"h":19},{"content":"정의에 해당하는 경우 보험금 지급대상이 되나 그렇지 않은 경우 보험금을 지급하지 않습니다.","x":131,"y":974,"w":744,"h":19},{"content":"① 타인의 생명보험 가입 관련 사례","x":106,"y":1005,"w":281,"h":19},{"content":"A씨는 B씨의 자필서명이 이루어지지 않은 상태에서 B씨를 피보험자로 하는 OO보험을 가입하였고, 이후 B씨가 사망해 A씨는 보","x":131,"y":1035,"w":1011,"h":19},{"content":"험금을 청구하였으나, 보험회사는 계약 무효처리 및 보험금 지급이 어려움을 안내","x":131,"y":1060,"w":642,"h":19},{"content":"※ 유의(참고)사항","x":131,"y":1085,"w":140,"h":19},{"content":": 타인의 사망을 보험사고로 하는 보험계약에는 보험계약 체결시 그 타인의 서면에 의한 동의를 얻어야 함,","x":270,"y":1085,"w":849,"h":19},{"content":"그렇지 않은 경우 무효 처리됨","x":131,"y":1110,"w":238,"h":19},{"content":"② 보험금청구권 소멸시효 관련 사례","x":106,"y":1141,"w":290,"h":19},{"content":"OO상해보험을 가입한 A씨는 길을 가다 넘어지는 사고로 일주일간 병원치료를 받고 잊고 지내다가","x":131,"y":1171,"w":784,"h":19},{"content":"보험사고일로부터","x":914,"y":1171,"w":138,"h":19},{"content":"3년이 경","x":1051,"y":1171,"w":78,"h":19},{"content":"과한 후 보험금을 청구하였으나 보험회사는 보험금청구권의 소멸시효가 완성되어 보험금 지급이 어려움을 안내","x":131,"y":1196,"w":876,"h":19},{"content":"※유의(참고)사항","x":131,"y":1221,"w":132,"h":19},{"content":": 보험금청구권의 소멸시효 기간은 보험사고 내지 보험금 지급사유가 발생한 때로부터 3년이며, 3년의 소멸시","x":262,"y":1221,"w":869,"h":19},{"content":"효 기간동안 권리를 행사하지 않으면 소멸함","x":131,"y":1246,"w":349,"h":19},{"content":"마. 보험계약자 보험에 관한 사항","x":57,"y":1288,"w":393,"h":28},{"content":"① 예금자보호제도","x":57,"y":1328,"w":170,"h":22},{"content":"이 보험계약은 예금자보호법에 따라 해약환급금(또는 만기 시 보험금)에 기타지급금을 합한 금액이 1인당 \"1억원까지\"","x":171,"y":1356,"w":917,"h":19},{"content":"(본 보험회사의 여타 보호상품과 합산)보호됩니다. 이와 별도로 본 보험회사 보호상품의 사고보험금을 합산한 금액이","x":171,"y":1380,"w":917,"h":19},{"content":"1인당 \"1억원까지\"보호됩니다.","x":171,"y":1405,"w":224,"h":19},{"content":"다만, 보험계약자 및 보험료납부자가 법인인 보험계약의 경우에는 보호되지 않습니다","x":171,"y":1430,"w":669,"h":19},{"content":"② 상품별 주요민원사항","x":74,"y":1467,"w":220,"h":22},{"content":"11024266116270000020260410160145_20002014280","x":29,"y":9,"w":249,"h":10},{"content":"No : 1(000035) 【 35/139 】","x":676,"y":26,"w":215,"h":16},{"content":"<35>","x":1105,"y":26,"w":39,"h":16}]}